{
  "2592049": {
    "tripId": "2592049",
    "routeId": "15778",
    "delay": 60,
    "time": "1583678820",
    "nextStopId": "14124"
  },
  "2581971": {
    "tripId": "2581971",
    "routeId": "15720"
  },
  "2588560": {
    "tripId": "2588560",
    "routeId": "15757"
  },
  "2588986": {
    "tripId": "2588986",
    "routeId": "15760",
    "delay": -120,
    "time": "1583679480",
    "nextStopId": "16090"
  },
  "2583709": {
    "tripId": "2583709",
    "routeId": "15730",
    "delay": 60,
    "time": "1583680380",
    "nextStopId": "3777"
  },
  "2586169": {
    "tripId": "2586169",
    "routeId": "15746",
    "delay": 180,
    "time": "1583680380",
    "nextStopId": "4969"
  },
  "2585886": {
    "tripId": "2585886",
    "routeId": "15744"
  },
  "2584687": {
    "tripId": "2584687",
    "routeId": "15736",
    "delay": -60,
    "time": "1583679540",
    "nextStopId": "14425"
  },
  "2584671": {
    "tripId": "2584671",
    "routeId": "15736",
    "delay": 240,
    "time": "1583678340",
    "nextStopId": "2545"
  },
  "2582428": {
    "tripId": "2582428",
    "routeId": "15723",
    "delay": -60,
    "time": "1583678340",
    "nextStopId": "412"
  },
  "2586284": {
    "tripId": "2586284",
    "routeId": "15747",
    "delay": 60,
    "time": "1583680080",
    "nextStopId": "16231"
  },
  "2591727": {
    "tripId": "2591727",
    "routeId": "15776",
    "delay": -60,
    "time": "1583678700",
    "nextStopId": "12630"
  },
  "2583116": {
    "tripId": "2583116",
    "routeId": "15726",
    "delay": 180,
    "time": "1583679180",
    "nextStopId": "7653"
  },
  "2583061": {
    "tripId": "2583061",
    "routeId": "15726"
  },
  "2586136": {
    "tripId": "2586136",
    "routeId": "15746",
    "delay": 60,
    "time": "1583679660",
    "nextStopId": "5016"
  },
  "2582809": {
    "tripId": "2582809",
    "routeId": "15725",
    "delay": -60,
    "time": "1583679180",
    "nextStopId": "14792"
  },
  "2588099": {
    "tripId": "2588099",
    "routeId": "15755",
    "delay": -120,
    "time": "1583678940",
    "nextStopId": "249"
  },
  "2582780": {
    "tripId": "2582780",
    "routeId": "15725",
    "delay": 600,
    "time": "1583679540",
    "nextStopId": "768"
  },
  "2588681": {
    "tripId": "2588681",
    "routeId": "15758"
  },
  "2588696": {
    "tripId": "2588696",
    "routeId": "15758",
    "delay": 60,
    "time": "1583679060",
    "nextStopId": "13330"
  },
  "2589010": {
    "tripId": "2589010",
    "routeId": "15760",
    "delay": 60,
    "time": "1583679060",
    "nextStopId": "16146"
  },
  "2589442": {
    "tripId": "2589442",
    "routeId": "15762",
    "delay": -60,
    "time": "1583679600",
    "nextStopId": "16090"
  },
  "2582178": {
    "tripId": "2582178",
    "routeId": "15721"
  },
  "2589924": {
    "tripId": "2589924",
    "routeId": "15764",
    "delay": 60,
    "time": "1583677260",
    "nextStopId": "15707"
  },
  "2587743": {
    "tripId": "2587743",
    "routeId": "15753",
    "delay": -60,
    "time": "1583677800",
    "nextStopId": "15824"
  },
  "2587654": {
    "tripId": "2587654",
    "routeId": "15753"
  },
  "2587655": {
    "tripId": "2587655",
    "routeId": "15753",
    "delay": -120,
    "time": "1583678100",
    "nextStopId": "13487"
  },
  "2592347": {
    "tripId": "2592347",
    "routeId": "15782"
  },
  "2591689": {
    "tripId": "2591689",
    "routeId": "15776"
  },
  "2591454": {
    "tripId": "2591454",
    "routeId": "15774",
    "delay": -60,
    "time": "1583679420",
    "nextStopId": "12702"
  },
  "2590880": {
    "tripId": "2590880",
    "routeId": "15770",
    "delay": -60,
    "time": "1583680020",
    "nextStopId": "11102"
  },
  "2584019": {
    "tripId": "2584019",
    "routeId": "15732",
    "delay": -180,
    "time": "1583678820",
    "nextStopId": "14769"
  },
  "2585867": {
    "tripId": "2585867",
    "routeId": "15744",
    "delay": -60,
    "time": "1583678940",
    "nextStopId": "13330"
  },
  "2586428": {
    "tripId": "2586428",
    "routeId": "15748"
  },
  "2582406": {
    "tripId": "2582406",
    "routeId": "15723",
    "delay": 60,
    "time": "1583679060",
    "nextStopId": "14792"
  },
  "2590202": {
    "tripId": "2590202",
    "routeId": "15765",
    "delay": 60,
    "time": "1583680080",
    "nextStopId": "13487"
  },
  "2583239": {
    "tripId": "2583239",
    "routeId": "15727",
    "delay": 180,
    "time": "1583680200",
    "nextStopId": "3772"
  },
  "2590583": {
    "tripId": "2590583",
    "routeId": "15767"
  },
  "2590572": {
    "tripId": "2590572",
    "routeId": "15767",
    "delay": -120,
    "time": "1583678880",
    "nextStopId": "16063"
  },
  "2590887": {
    "tripId": "2590887",
    "routeId": "15770"
  },
  "2590928": {
    "tripId": "2590928",
    "routeId": "15770"
  },
  "2589647": {
    "tripId": "2589647",
    "routeId": "15763",
    "delay": -60,
    "time": "1583678580",
    "nextStopId": "2097"
  },
  "2584493": {
    "tripId": "2584493",
    "routeId": "15735",
    "delay": 60,
    "time": "1583679060",
    "nextStopId": "14496"
  },
  "2589427": {
    "tripId": "2589427",
    "routeId": "15762",
    "delay": 360,
    "time": "1583679120",
    "nextStopId": "768"
  },
  "2584547": {
    "tripId": "2584547",
    "routeId": "15735",
    "delay": 180,
    "time": "1583679720",
    "nextStopId": "7424"
  },
  "2589624": {
    "tripId": "2589624",
    "routeId": "15763",
    "delay": -60,
    "time": "1583678040",
    "nextStopId": "13659"
  },
  "2589625": {
    "tripId": "2589625",
    "routeId": "15763",
    "delay": 240,
    "time": "1583680140",
    "nextStopId": "13659"
  },
  "2587075": {
    "tripId": "2587075",
    "routeId": "15751"
  },
  "2582151": {
    "tripId": "2582151",
    "routeId": "15721",
    "delay": -120,
    "time": "1583678820",
    "nextStopId": "13330"
  },
  "2587742": {
    "tripId": "2587742",
    "routeId": "15753",
    "delay": -60,
    "time": "1583678700",
    "nextStopId": "15824"
  },
  "2588838": {
    "tripId": "2588838",
    "routeId": "15759",
    "delay": 60,
    "time": "1583679060",
    "nextStopId": "16146"
  },
  "2586822": {
    "tripId": "2586822",
    "routeId": "15750",
    "delay": -120,
    "time": "1583678880",
    "nextStopId": "13330"
  },
  "2592355": {
    "tripId": "2592355",
    "routeId": "15782"
  },
  "2594900": {
    "tripId": "2594900",
    "routeId": "15734",
    "delay": 420,
    "time": "1583680140",
    "nextStopId": "14942"
  },
  "2586150": {
    "tripId": "2586150",
    "routeId": "15746",
    "delay": 60,
    "time": "1583680320",
    "nextStopId": "14938"
  },
  "2583846": {
    "tripId": "2583846",
    "routeId": "15731",
    "delay": 240,
    "time": "1583679240",
    "nextStopId": "7653"
  },
  "2588861": {
    "tripId": "2588861",
    "routeId": "15759",
    "delay": -60,
    "time": "1583678940",
    "nextStopId": "13330"
  },
  "2590402": {
    "tripId": "2590402",
    "routeId": "15766"
  },
  "2589877": {
    "tripId": "2589877",
    "routeId": "15764",
    "delay": 60,
    "time": "1583677500",
    "nextStopId": "14495"
  },
  "2590444": {
    "tripId": "2590444",
    "routeId": "15766",
    "delay": 60,
    "time": "1583679060",
    "nextStopId": "15707"
  },
  "2588450": {
    "tripId": "2588450",
    "routeId": "15756",
    "delay": -60,
    "time": "1583679000",
    "nextStopId": "7852"
  },
  "2585016": {
    "tripId": "2585016",
    "routeId": "15738",
    "delay": 60,
    "time": "1583680440",
    "nextStopId": "7424"
  },
  "2586882": {
    "tripId": "2586882",
    "routeId": "15750",
    "delay": 60,
    "time": "1583679960",
    "nextStopId": "16090"
  },
  "2591149": {
    "tripId": "2591149",
    "routeId": "15771"
  },
  "2592085": {
    "tripId": "2592085",
    "routeId": "15778",
    "delay": 360,
    "time": "1583680440",
    "nextStopId": "12040"
  },
  "2590234": {
    "tripId": "2590234",
    "routeId": "15765",
    "delay": 120,
    "time": "1583679960",
    "nextStopId": "768"
  },
  "2585729": {
    "tripId": "2585729",
    "routeId": "15743"
  },
  "2590235": {
    "tripId": "2590235",
    "routeId": "15765"
  },
  "2583500": {
    "tripId": "2583500",
    "routeId": "15728"
  },
  "2583499": {
    "tripId": "2583499",
    "routeId": "15728",
    "delay": 120,
    "time": "1583679900",
    "nextStopId": "6649"
  },
  "2582810": {
    "tripId": "2582810",
    "routeId": "15725"
  },
  "2594095": {
    "tripId": "2594095",
    "routeId": "15768"
  },
  "2589428": {
    "tripId": "2589428",
    "routeId": "15762",
    "delay": -60,
    "time": "1583676900",
    "nextStopId": "768"
  },
  "2592086": {
    "tripId": "2592086",
    "routeId": "15778",
    "delay": -60,
    "time": "1583678220",
    "nextStopId": "12040"
  },
  "2588144": {
    "tripId": "2588144",
    "routeId": "15755",
    "delay": 180,
    "time": "1583678880",
    "nextStopId": "3913"
  },
  "2583535": {
    "tripId": "2583535",
    "routeId": "15728",
    "delay": -120,
    "time": "1583678040",
    "nextStopId": "14769"
  },
  "2584740": {
    "tripId": "2584740",
    "routeId": "15737"
  },
  "2587653": {
    "tripId": "2587653",
    "routeId": "15753",
    "delay": -60,
    "time": "1583679960",
    "nextStopId": "13487"
  },
  "2591865": {
    "tripId": "2591865",
    "routeId": "15777",
    "delay": 120,
    "time": "1583680380",
    "nextStopId": "12702"
  },
  "2583875": {
    "tripId": "2583875",
    "routeId": "15731",
    "delay": 60,
    "time": "1583678220",
    "nextStopId": "7424"
  },
  "2590203": {
    "tripId": "2590203",
    "routeId": "15765",
    "delay": 180,
    "time": "1583678400",
    "nextStopId": "13487"
  },
  "2582781": {
    "tripId": "2582781",
    "routeId": "15725",
    "delay": 60,
    "time": "1583677200",
    "nextStopId": "768"
  },
  "2589925": {
    "tripId": "2589925",
    "routeId": "15764",
    "delay": -120,
    "time": "1583678880",
    "nextStopId": "15707"
  },
  "2589878": {
    "tripId": "2589878",
    "routeId": "15764",
    "delay": -120,
    "time": "1583679120",
    "nextStopId": "14495"
  },
  "2590927": {
    "tripId": "2590927",
    "routeId": "15770",
    "delay": 60,
    "time": "1583679780",
    "nextStopId": "14330"
  },
  "2587223": {
    "tripId": "2587223",
    "routeId": "15752",
    "delay": 60,
    "time": "1583679060",
    "nextStopId": "13967"
  },
  "2582575": {
    "tripId": "2582575",
    "routeId": "15724",
    "delay": -180,
    "time": "1583680020",
    "nextStopId": "8155"
  },
  "2585457": {
    "tripId": "2585457",
    "routeId": "15741",
    "delay": 180,
    "time": "1583680440",
    "nextStopId": "6126"
  },
  "2581953": {
    "tripId": "2581953",
    "routeId": "15720"
  },
  "2587844": {
    "tripId": "2587844",
    "routeId": "15754",
    "delay": -120,
    "time": "1583678400",
    "nextStopId": "5858"
  },
  "2586556": {
    "tripId": "2586556",
    "routeId": "15749",
    "delay": 240,
    "time": "1583679540",
    "nextStopId": "6649"
  }
}